tinybee/__init__.py
tinybee/__main__.py
tinybee/align_texts.py
tinybee/cmat2tset.py
tinybee/cos_matrix2.py
tinybee/dbscan_pairs.py
tinybee/embed_text.py
tinybee/fetch_sent_corr.py
tinybee/find_pairs-.py-
tinybee/find_pairs.py
tinybee/gen_aset.py
tinybee/gen_iset.py
tinybee/gen_row_align.py
tinybee/gen_row_alignment.py
tinybee/gen_row_alignment.py-
tinybee/interpolate_pset.py
tinybee/linregress_tset.py
tinybee/lowess_pairs.py
tinybee/lrtrace_tset.py
tinybee/optics_trace.py
tinybee/plot_tset.py
tinybee/snsrel_yargmax_max.py
tinybee/zip_longest_middle.py
tinybee-0.1.5.dist-info/WHEEL
tinybee-0.1.5.dist-info/METADATA
tinybee-0.1.5.dist-info/RECORD
